{
  "title": "",
  "outline": [
    {
      "level": "H1",
      "text": "Ontario’s Libraries",
      "page": 0
    },
    {
      "level": "H1",
      "text": "Working Together",
      "page": 0
    },
    {
      "level": "H1",
      "text": "To Present a Proposal for Developing",
      "page": 0
    },
    {
      "level": "H1",
      "text": "Ontario’s Digital Library",
      "page": 1
    },
    {
      "level": "H1",
      "text": "A Critical Component for Implementing Ontario’s Road Map to",
      "page": 1
    },
    {
      "level": "H1",
      "text": "Prosperity Strategy",
      "page": 1
    },
    {
      "level": "H2",
      "text": "Summary",
      "page": 1
    },
    {
      "level": "H1",
      "text": "This business plan must be completed and approved by the ODL Steering Committee no",
      "page": 1
    },
    {
      "level": "H3",
      "text": "Timeline:",
      "page": 1
    },
    {
      "level": "H1",
      "text": "Please note that we reserve the right not to select any of the submitted proposals and may",
      "page": 2
    },
    {
      "level": "H2",
      "text": "Background",
      "page": 2
    },
    {
      "level": "H1",
      "text": "Libraries that serve very different clientele recognize that by working together they can create",
      "page": 2
    },
    {
      "level": "H3",
      "text": "The principles which will define and guide the ODL are:",
      "page": 3
    },
    {
      "level": "H3",
      "text": "Equitable access for all Ontarians:",
      "page": 3
    },
    {
      "level": "H1",
      "text": "Ontario citizens",
      "page": 3
    },
    {
      "level": "H1",
      "text": "We will eliminate barriers to the access to information and create more consistent",
      "page": 3
    },
    {
      "level": "H1",
      "text": "We will facilitate consensus among members regarding ODL’s portfolio of electronic",
      "page": 3
    },
    {
      "level": "H1",
      "text": "We will balance the interests and realities of small and large as well as rich and poor",
      "page": 3
    },
    {
      "level": "H3",
      "text": "Shared governance structure:",
      "page": 3
    },
    {
      "level": "H3",
      "text": "Shared funding:",
      "page": 3
    },
    {
      "level": "H1",
      "text": "We will be willing to pool talents and dollars in order to provide common services that are",
      "page": 3
    },
    {
      "level": "H3",
      "text": "Local points of entry:",
      "page": 4
    },
    {
      "level": "H3",
      "text": "Services envisioned for the ODL’s include:",
      "page": 4
    },
    {
      "level": "H3",
      "text": "Access:",
      "page": 4
    },
    {
      "level": "H3",
      "text": "Guidance and Advice:",
      "page": 4
    },
    {
      "level": "H3",
      "text": "Training:",
      "page": 4
    },
    {
      "level": "H3",
      "text": "Technological Support:",
      "page": 4
    },
    {
      "level": "H3",
      "text": "What could the ODL really mean?",
      "page": 4
    },
    {
      "level": "H3",
      "text": "For each Ontario citizen it could mean:",
      "page": 4
    },
    {
      "level": "H1",
      "text": "One local point of entry to access seamless electronic library services and",
      "page": 4
    },
    {
      "level": "H1",
      "text": "Electronic information and tools that enhance job skills and the learning",
      "page": 4
    },
    {
      "level": "H3",
      "text": "For each Ontario student it could mean:",
      "page": 4
    },
    {
      "level": "H3",
      "text": "For each Ontario library it could mean:",
      "page": 5
    },
    {
      "level": "H1",
      "text": "One point of entry for themselves and their clientele to quality electronic",
      "page": 5
    },
    {
      "level": "H3",
      "text": "For the Ontario government it could mean:",
      "page": 5
    },
    {
      "level": "H1",
      "text": "Improved access and flexibility for all students at all ages and stages",
      "page": 5
    },
    {
      "level": "H1",
      "text": "The opportunity to address emerging job skills shortages and facilitate school",
      "page": 5
    },
    {
      "level": "H1",
      "text": "The Business Plan to be Developed",
      "page": 5
    },
    {
      "level": "H1",
      "text": "The business plan which needs to be developed for the ODL must be a formal business plan",
      "page": 5
    },
    {
      "level": "H1",
      "text": "The process of developing this business plan must be extremely consultative to ensure that",
      "page": 6
    },
    {
      "level": "H3",
      "text": "Milestones",
      "page": 6
    },
    {
      "level": "H1",
      "text": "Approach and Specific Proposal Requirements",
      "page": 6
    },
    {
      "level": "H3",
      "text": "The proposal should include the following information:",
      "page": 6
    },
    {
      "level": "H1",
      "text": "Evaluation and Awarding of Contract",
      "page": 7
    },
    {
      "level": "H1",
      "text": "Demonstrated experience",
      "page": 7
    },
    {
      "level": "H1",
      "text": "Timeline and projected completion date",
      "page": 7
    },
    {
      "level": "H1",
      "text": "Other relevant factors as determined by the ODL Steering Committee",
      "page": 7
    },
    {
      "level": "H1",
      "text": "Bidders are asked not to contact any other member of the ODL Catalyst Team or the ODL Steering",
      "page": 7
    },
    {
      "level": "H2",
      "text": "Appendix A: ODL Envisioned Phases & Funding",
      "page": 8
    },
    {
      "level": "H3",
      "text": "Phase I: Business Planning",
      "page": 8
    },
    {
      "level": "H3",
      "text": "Phase II: Implementing and Transitioning",
      "page": 8
    },
    {
      "level": "H1",
      "text": "The seed money requested will allow libraries to realign their budgets and services as the infrastructure",
      "page": 8
    },
    {
      "level": "H3",
      "text": "Phase III: Operating and Growing the ODL",
      "page": 8
    },
    {
      "level": "H1",
      "text": "The ongoing funding of the ODL will be based on a partnership model involving all the key participants",
      "page": 9
    },
    {
      "level": "H1",
      "text": "OVERVIEW OF ODL FUNDING MODEL",
      "page": 9
    },
    {
      "level": "H2",
      "text": "Appendix B: ODL Steering Committee Terms of Reference",
      "page": 10
    },
    {
      "level": "H3",
      "text": "1. Preamble",
      "page": 10
    },
    {
      "level": "H3",
      "text": "2. Terms of Reference",
      "page": 10
    },
    {
      "level": "H3",
      "text": "3. Membership",
      "page": 10
    },
    {
      "level": "H3",
      "text": "4. Appointment Criteria and Process",
      "page": 11
    },
    {
      "level": "H3",
      "text": "5. Term",
      "page": 11
    },
    {
      "level": "H1",
      "text": "Expected term on the Steering Committee is the time required to complete development of the",
      "page": 11
    },
    {
      "level": "H3",
      "text": "6. Chair",
      "page": 11
    },
    {
      "level": "H3",
      "text": "Role of the Chair:",
      "page": 11
    },
    {
      "level": "H3",
      "text": "7. Meetings",
      "page": 11
    },
    {
      "level": "H3",
      "text": "8. Lines of Accountability and Communication",
      "page": 11
    },
    {
      "level": "H3",
      "text": "9. Financial and Administrative Policies",
      "page": 12
    },
    {
      "level": "H1",
      "text": "The ODL Steering Committee will function according to standard conflict of interest guidelines",
      "page": 12
    },
    {
      "level": "H2",
      "text": "Appendix C: ODL’s Envisioned Electronic Resources",
      "page": 13
    },
    {
      "level": "H1",
      "text": "The purpose of the ODL is to provide equal access to information for all Ontario citizens through",
      "page": 13
    },
    {
      "level": "H3",
      "text": "1. Reference Resources",
      "page": 13
    },
    {
      "level": "H3",
      "text": "2. Subject Guides",
      "page": 13
    }
  ]
}